otodus/__init__.py
otodus/otodus.py
otodus/prompts/auth_bypass.txt
otodus/prompts/command_injection.txt
otodus/prompts/idor.txt
otodus/prompts/lfi.txt
otodus/prompts/open_redirect.txt
otodus/prompts/sql_injection.txt
otodus/prompts/ssrf.txt
otodus/prompts/xss_reflected.txt
otodus-1.0.2.dist-info/licenses/LICENSE
otodus-1.0.2.dist-info/METADATA
otodus-1.0.2.dist-info/WHEEL
otodus-1.0.2.dist-info/entry_points.txt
otodus-1.0.2.dist-info/top_level.txt
otodus-1.0.2.dist-info/RECORD
