Metadata-Version: 2.4
Name: otodus
Version: 1.0.2
Summary: Otodus - The Megalodon of Automated Pentesting with AI Agents
Home-page: https://github.com/IMApurbo/otodus
Author: AKM Korishee Apurbo
Author-email: bandinvisible8@gmail.com
License: MIT
Project-URL: Bug Tracker, https://github.com/IMApurbo/otodus/issues
Project-URL: Source Code, https://github.com/IMApurbo/otodus
Classifier: Programming Language :: Python :: 3
Classifier: Programming Language :: Python :: 3.8
Classifier: Programming Language :: Python :: 3.9
Classifier: Programming Language :: Python :: 3.10
Classifier: Programming Language :: Python :: 3.11
Classifier: Programming Language :: Python :: 3.12
Classifier: License :: OSI Approved :: MIT License
Classifier: Operating System :: OS Independent
Classifier: Topic :: Security
Classifier: Intended Audience :: Information Technology
Classifier: Development Status :: 4 - Beta
Requires-Python: >=3.8
License-File: LICENSE
Requires-Dist: Flask>=2.0.0
Requires-Dist: requests>=2.28.0
Requires-Dist: crawlerx==1.1.1
Requires-Dist: platformdirs>=4.0.0
Dynamic: author
Dynamic: author-email
Dynamic: classifier
Dynamic: description
Dynamic: description-content-type
Dynamic: home-page
Dynamic: license
Dynamic: license-file
Dynamic: project-url
Dynamic: requires-dist
Dynamic: requires-python
Dynamic: summary
